bangla_news_mcp/__init__.py
bangla_news_mcp/__main__.py
bangla_news_mcp/server.py
bangla_news_mcp/test.py
bangla_news_mcp/web_client.py
bangla_news_mcp-1.0.2.dist-info/licenses/LICENSE
bangla_news_mcp-1.0.2.dist-info/METADATA
bangla_news_mcp-1.0.2.dist-info/WHEEL
bangla_news_mcp-1.0.2.dist-info/entry_points.txt
bangla_news_mcp-1.0.2.dist-info/top_level.txt
bangla_news_mcp-1.0.2.dist-info/RECORD
