Metadata-Version: 2.4
Name: bangla-news-mcp
Version: 1.0.2
Summary: A Model Context Protocol (MCP) server that retrieves bangla news to provide context to LLMs.
Author-email: Abid Mohammad Jawad <abidmohammadjawad@gmail.com>
License: MIT
Requires-Python: >=3.10
License-File: LICENSE
Requires-Dist: mcp>=1.0.0
Dynamic: license-file
